{
  "name": "CANCER_RISK_SCORE_AGE",
  "description": "This table contains the age associated with a risk score.",
  "primaryKey": [
    {
      "columnName": "PAT_ENC_CSN_ID",
      "ordinalPosition": 1
    },
    {
      "columnName": "GROUP_LINE",
      "ordinalPosition": 2
    },
    {
      "columnName": "VALUE_LINE",
      "ordinalPosition": 3
    }
  ],
  "columns": [
    {
      "ordinalPosition": 1,
      "name": "PAT_ENC_CSN_ID",
      "type": "NUMERIC",
      "discontinued": false,
      "description": "The unique contact serial number for this contact. This number is unique across all patient encounters in your system. If you use IntraConnect, this is the Unique Contact Identifier (UCI)."
    },
    {
      "ordinalPosition": 2,
      "name": "GROUP_LINE",
      "type": "INTEGER",
      "discontinued": false,
      "description": "The line number for the information associated with this contact."
    },
    {
      "ordinalPosition": 3,
      "name": "VALUE_LINE",
      "type": "INTEGER",
      "discontinued": false,
      "description": "The line number of one of the multiple values associated with a specific group of data within this contact."
    },
    {
      "ordinalPosition": 4,
      "name": "SCORE_AGE",
      "type": "INTEGER",
      "discontinued": false,
      "description": "The patient's age for which the risk score applies."
    }
  ]
}
