{
  "name": "CARE_COORDINATION",
  "description": "This table will contain data relevant to the Ambulatory patient Care Coordination. Currently this is just the Care Coordination note.",
  "primaryKey": [
    {
      "columnName": "PAT_ID",
      "ordinalPosition": 1
    }
  ],
  "columns": [
    {
      "ordinalPosition": 1,
      "name": "PAT_ID",
      "type": "VARCHAR",
      "discontinued": false,
      "description": "The unique ID assigned to the patient record. This ID may be encrypted if you have elected to use enterprise reporting's encryption utility."
    },
    {
      "ordinalPosition": 2,
      "name": "CARE_COORD_NOTE_ID",
      "type": "VARCHAR",
      "discontinued": false,
      "description": "Stores the ID of the Care Coordination note."
    }
  ]
}
