{
  "name": "CLARITY_VENDOR",
  "description": "The CLARITY_VENDOR table contains basic data about the various organizations to which you pay checks. These vendors may receive AP claims payments, PCP capitation, or specialty capitation payments.",
  "primaryKey": [
    {
      "columnName": "VENDOR_ID",
      "ordinalPosition": 1
    }
  ],
  "columns": [
    {
      "ordinalPosition": 1,
      "name": "VENDOR_ID",
      "type": "VARCHAR",
      "discontinued": false,
      "description": "The unique internal ID assigned to the vendor record. This ID should be used for linking purposes on enterprise reporting reports; however, it is typically not displayed to users and should not be included on the report output. Users will be familiar with VENDOR_EXTERNAL_ID."
    },
    {
      "ordinalPosition": 2,
      "name": "VENDOR_ID_VENDOR_NAME",
      "type": "VARCHAR",
      "discontinued": false,
      "description": "The name of the vendor."
    },
    {
      "ordinalPosition": 3,
      "name": "VENDOR_NAME",
      "type": "VARCHAR",
      "discontinued": false,
      "description": "The name of the vendor."
    }
  ]
}
