{
  "name": "HSP_ACCT_PXA_PRVRO",
  "description": "This table extracts the related multiple response ICD PX - ALT - Other Provider Role (I HAR 3131) item.",
  "primaryKey": [
    {
      "columnName": "ACCT_ID",
      "ordinalPosition": 1
    },
    {
      "columnName": "GROUP_LINE",
      "ordinalPosition": 2
    },
    {
      "columnName": "VALUE_LINE",
      "ordinalPosition": 3
    }
  ],
  "columns": [
    {
      "ordinalPosition": 1,
      "name": "ACCT_ID",
      "type": "NUMERIC",
      "discontinued": false,
      "description": "The unique identifier (.1 item) for the hospital account record."
    },
    {
      "ordinalPosition": 2,
      "name": "GROUP_LINE",
      "type": "INTEGER",
      "discontinued": false,
      "description": "The line number for the information associated with this record."
    },
    {
      "ordinalPosition": 3,
      "name": "VALUE_LINE",
      "type": "INTEGER",
      "discontinued": false,
      "description": "The unique identifier for the price estimate record."
    },
    {
      "ordinalPosition": 4,
      "name": "IPXA_OTH_PROV_RL_C_NAME",
      "type": "VARCHAR",
      "discontinued": false,
      "description": "The unique identifier for the price estimate record."
    }
  ]
}
