{
  "name": "INV_COND_CODE",
  "description": "This table holds the condition codes sent out on professional billing claims.",
  "primaryKey": [
    {
      "columnName": "INVOICE_ID",
      "ordinalPosition": 1
    },
    {
      "columnName": "LINE",
      "ordinalPosition": 2
    }
  ],
  "columns": [
    {
      "ordinalPosition": 1,
      "name": "INVOICE_ID",
      "type": "NUMERIC",
      "discontinued": false,
      "description": "The invoice record ID."
    },
    {
      "ordinalPosition": 2,
      "name": "LINE",
      "type": "INTEGER",
      "discontinued": false,
      "description": "Returns the line count value for multiple or related response items."
    },
    {
      "ordinalPosition": 3,
      "name": "CONDITION_CODE_C_NAME",
      "type": "VARCHAR",
      "discontinued": false,
      "description": "Condition Code to print on claims."
    },
    {
      "ordinalPosition": 4,
      "name": "INV_NUM_COND_PTR100",
      "type": "INTEGER",
      "discontinued": false,
      "description": "Stores an index into the invoice line for the invoice number."
    }
  ]
}
