{
  "name": "INVOICE",
  "description": "This table includes the basic data for the invoice (INV) record. It contains one row for each used INV record (excluding unused pre-allocated invoices). Note that a row in this table can correspond to multiple claims sent.",
  "primaryKey": [
    {
      "columnName": "INVOICE_ID",
      "ordinalPosition": 1
    }
  ],
  "columns": [
    {
      "ordinalPosition": 1,
      "name": "INVOICE_ID",
      "type": "NUMERIC",
      "discontinued": false,
      "description": "The Invoice ID."
    },
    {
      "ordinalPosition": 2,
      "name": "PAT_ID",
      "type": "VARCHAR",
      "discontinued": false,
      "description": "The patient ID associated with this invoice."
    },
    {
      "ordinalPosition": 3,
      "name": "ACCOUNT_ID",
      "type": "NUMERIC",
      "discontinued": false,
      "description": "The account ID that is associated with this invoice."
    },
    {
      "ordinalPosition": 4,
      "name": "SERV_AREA_ID",
      "type": "NUMERIC",
      "discontinued": false,
      "description": "The ID of the service area associated with this invoice."
    },
    {
      "ordinalPosition": 5,
      "name": "LOC_ID",
      "type": "NUMERIC",
      "discontinued": false,
      "description": "The ID of the revenue location associated with this invoice."
    },
    {
      "ordinalPosition": 6,
      "name": "POS_ID",
      "type": "NUMERIC",
      "discontinued": false,
      "description": "The ID of the place of service associated with this invoice."
    },
    {
      "ordinalPosition": 7,
      "name": "DEPARTMENT_ID",
      "type": "NUMERIC",
      "discontinued": false,
      "description": "The ID of the department associated with this invoice."
    },
    {
      "ordinalPosition": 8,
      "name": "UB_COVERED_DAYS",
      "type": "INTEGER",
      "discontinued": false,
      "description": "The number of covered days for a uniform billing claim."
    },
    {
      "ordinalPosition": 9,
      "name": "UB_NON_COVERED_DAYS",
      "type": "INTEGER",
      "discontinued": false,
      "description": "The number of non-covered days for a uniform billing claim."
    },
    {
      "ordinalPosition": 10,
      "name": "UB_COINSURANCE_DAYS",
      "type": "INTEGER",
      "discontinued": false,
      "description": "The number of coinsurance days for the uniform billing claim."
    },
    {
      "ordinalPosition": 11,
      "name": "UB_PRINCIPA_DIAG_ID",
      "type": "NUMERIC",
      "discontinued": false,
      "description": "The principal diagnosis for the uniform billing claim."
    },
    {
      "ordinalPosition": 12,
      "name": "UB_TYPE_OF_BILL_STR",
      "type": "VARCHAR",
      "discontinued": false,
      "description": "Stores the type of bill that was sent out on the claim."
    },
    {
      "ordinalPosition": 13,
      "name": "PROV_ID",
      "type": "VARCHAR",
      "discontinued": false,
      "description": "Stores the ID of the billing provider associated with the invoice."
    },
    {
      "ordinalPosition": 14,
      "name": "ACCT_SERIAL_NUM",
      "type": "INTEGER",
      "discontinued": false,
      "description": "Stores the account serial number associated with the invoice."
    },
    {
      "ordinalPosition": 15,
      "name": "PAT_SERIAL_NUM",
      "type": "INTEGER",
      "discontinued": false,
      "description": "Stores the patient serial number associated with the invoice."
    },
    {
      "ordinalPosition": 16,
      "name": "RQG_ID",
      "type": "NUMERIC",
      "discontinued": false,
      "description": "Stores the requisition grouper ID associated with the invoice when there is no patient record."
    },
    {
      "ordinalPosition": 17,
      "name": "TAX_ID",
      "type": "VARCHAR",
      "discontinued": false,
      "description": "Stores the tax ID associated with the invoice."
    },
    {
      "ordinalPosition": 18,
      "name": "TAX_ID_TYPE",
      "type": "VARCHAR",
      "discontinued": false,
      "description": "Stores the type of tax ID associated with the invoice."
    },
    {
      "ordinalPosition": 19,
      "name": "TREATMENT_PLAN_ID",
      "type": "VARCHAR",
      "discontinued": false,
      "description": "Stores the treatment plan ID associated with the invoice."
    },
    {
      "ordinalPosition": 20,
      "name": "INSURANCE_AMT",
      "type": "NUMERIC",
      "discontinued": false,
      "description": "Stores the insurance amount for the invoice."
    },
    {
      "ordinalPosition": 21,
      "name": "SELF_PAY_AMT",
      "type": "NUMERIC",
      "discontinued": false,
      "description": "Stores the initial self-pay amount for the invoice."
    },
    {
      "ordinalPosition": 22,
      "name": "INIT_INSURANCE_BAL",
      "type": "NUMERIC",
      "discontinued": false,
      "description": "Stores the initial insurance amount for the invoice."
    },
    {
      "ordinalPosition": 23,
      "name": "INIT_SELF_PAY_BAL",
      "type": "NUMERIC",
      "discontinued": false,
      "description": "Stores the initial self-pay amount for the invoice."
    },
    {
      "ordinalPosition": 24,
      "name": "BILL_AREA_ID",
      "type": "NUMERIC",
      "discontinued": false,
      "description": "Stores the bill area associated with the invoice."
    },
    {
      "ordinalPosition": 25,
      "name": "BILL_AREA_ID_BILL_AREA_NAME",
      "type": "VARCHAR",
      "discontinued": false,
      "description": "The record name of this bill area, financial subdivision, or financial division."
    },
    {
      "ordinalPosition": 26,
      "name": "PB_HOSP_ACT_ID",
      "type": "NUMERIC",
      "discontinued": false,
      "description": "The Professional Billing Hospital Account ID."
    },
    {
      "ordinalPosition": 27,
      "name": "RECORD_STATUS_C_NAME",
      "type": "VARCHAR",
      "discontinued": false,
      "description": "This column shows the status of the invoice record.",
      "entries": [
        "Active",
        "Inactive",
        "Deleted",
        "Inactive and Deleted",
        "Hidden",
        "Inactive and Hidden",
        "Deleted and Hidden",
        "Inactive Deleted and Hidden"
      ]
    }
  ]
}
