{
  "name": "IP_HANDOFF",
  "description": "The table contains information of a handoff field.",
  "primaryKey": [
    {
      "columnName": "HANDOFF_ID",
      "ordinalPosition": 1
    }
  ],
  "columns": [
    {
      "ordinalPosition": 1,
      "name": "HANDOFF_ID",
      "type": "NUMERIC",
      "discontinued": false,
      "description": "The unique identifier (.1 item) for the handoff data record."
    },
    {
      "ordinalPosition": 2,
      "name": "PAT_CSN_ID",
      "type": "NUMERIC",
      "discontinued": false,
      "description": "The contact serial number (CSN) of the patient contact on which the Handoff was written."
    },
    {
      "ordinalPosition": 3,
      "name": "SERVICE_C_NAME",
      "type": "VARCHAR",
      "discontinued": false,
      "description": "The service of the handoff field."
    },
    {
      "ordinalPosition": 4,
      "name": "PURPOSE_C_NAME",
      "type": "VARCHAR",
      "discontinued": false,
      "description": "This item defines the purpose of the handoff field.",
      "entries": [
        "Summary",
        "To Do",
        "Medications",
        "Labs",
        "Imaging"
      ]
    },
    {
      "ordinalPosition": 5,
      "name": "INSTANT_OF_UPDATE_DTTM",
      "type": "DATETIME (Local) ",
      "discontinued": false,
      "description": "This item stores the instant the record was last locked/unlocked."
    }
  ]
}
