{
  "name": "MAR_EDIT_COSN_INST",
  "description": "Audit trail for list of instants at which this med administration was cosigned.",
  "primaryKey": [
    {
      "columnName": "ORDER_ID",
      "ordinalPosition": 1
    },
    {
      "columnName": "GROUP_LINE",
      "ordinalPosition": 2
    },
    {
      "columnName": "VALUE_LINE",
      "ordinalPosition": 3
    }
  ],
  "columns": [
    {
      "ordinalPosition": 1,
      "name": "ORDER_ID",
      "type": "NUMERIC",
      "discontinued": false,
      "description": "The unique identifier (.1 item) for the order record."
    },
    {
      "ordinalPosition": 2,
      "name": "GROUP_LINE",
      "type": "INTEGER",
      "discontinued": false,
      "description": "The line number for the information associated with this record."
    },
    {
      "ordinalPosition": 3,
      "name": "VALUE_LINE",
      "type": "INTEGER",
      "discontinued": false,
      "description": "The line number of one of the multiple values associated with a specific group of data within this record."
    },
    {
      "ordinalPosition": 4,
      "name": "EDIT_COSIGN_INSTANT",
      "type": "NUMERIC",
      "discontinued": false,
      "description": "Audit trail for cosign instant"
    }
  ]
}
