{
  "name": "MC_PRICER_MSG_INPUT",
  "description": "This table contains core CMS message input data from the Epic Pricer.",
  "primaryKey": [
    {
      "columnName": "PRICER_MSG_ID",
      "ordinalPosition": 1
    },
    {
      "columnName": "LINE",
      "ordinalPosition": 2
    }
  ],
  "columns": [
    {
      "ordinalPosition": 1,
      "name": "PRICER_MSG_ID",
      "type": "NUMERIC",
      "discontinued": false,
      "description": "The unique identifier for the Epic Pricer message record."
    },
    {
      "ordinalPosition": 2,
      "name": "LINE",
      "type": "INTEGER",
      "discontinued": false,
      "description": "The line number for the information associated with this record. Multiple pieces of information can be associated with this record."
    },
    {
      "ordinalPosition": 3,
      "name": "MSG_IN_NAME",
      "type": "VARCHAR",
      "discontinued": false,
      "description": "Node name for JSON representation of Epic Pricer input message."
    },
    {
      "ordinalPosition": 4,
      "name": "MSG_IN_VAL",
      "type": "VARCHAR",
      "discontinued": false,
      "description": "Node value for JSON representation of Epic Pricer input message."
    },
    {
      "ordinalPosition": 5,
      "name": "MSG_IN_PARENT",
      "type": "INTEGER",
      "discontinued": false,
      "description": "Parent node for JSON representation of Epic Pricer input message."
    },
    {
      "ordinalPosition": 6,
      "name": "MSG_IN_MC_NODE_TYPE_C_NAME",
      "type": "VARCHAR",
      "discontinued": false,
      "description": "Node type for JSON representation of Epic Pricer input message.",
      "entries": [
        "Array",
        "Object",
        "Node"
      ]
    }
  ]
}
