{
  "name": "OR_LOG_ALL_SURG",
  "description": "The OR_LOG_ALL_SURG table contains OR management system log surgeons.",
  "primaryKey": [
    {
      "columnName": "LOG_ID",
      "ordinalPosition": 1
    },
    {
      "columnName": "LINE",
      "ordinalPosition": 2
    }
  ],
  "columns": [
    {
      "ordinalPosition": 1,
      "name": "LOG_ID",
      "type": "VARCHAR",
      "discontinued": false,
      "description": "The unique ID of the surgical log which refers to the surgeon."
    },
    {
      "ordinalPosition": 2,
      "name": "LINE",
      "type": "INTEGER",
      "discontinued": false,
      "description": "The number of the line of the surgeon in this surgical log."
    },
    {
      "ordinalPosition": 3,
      "name": "SURG_ID",
      "type": "VARCHAR",
      "discontinued": false,
      "description": "The unique ID of the surgeon."
    },
    {
      "ordinalPosition": 4,
      "name": "ROLE_C_NAME",
      "type": "VARCHAR",
      "discontinued": false,
      "description": "The category value which represents the role for the corresponding surgeon in the surgical log.",
      "entries": [
        "Primary"
      ]
    },
    {
      "ordinalPosition": 5,
      "name": "SERVICE_C_NAME",
      "type": "VARCHAR",
      "discontinued": false,
      "description": "The category value which represents the kind of service the surgical log falls under."
    },
    {
      "ordinalPosition": 6,
      "name": "START_TIME",
      "type": "DATETIME (Local) ",
      "discontinued": false,
      "description": "The start date and time for the surgeon in the surgical log."
    },
    {
      "ordinalPosition": 7,
      "name": "END_TIME",
      "type": "DATETIME (Local) ",
      "discontinued": false,
      "description": "The end date and time for the surgeon in the surgical log."
    },
    {
      "ordinalPosition": 8,
      "name": "TOTAL_LENGTH",
      "type": "INTEGER",
      "discontinued": false,
      "description": "The total time a surgeon was needed in the surgical log in seconds."
    },
    {
      "ordinalPosition": 9,
      "name": "PANEL",
      "type": "INTEGER",
      "discontinued": false,
      "description": "The panel number in the surgical log in which the surgeon was involved."
    },
    {
      "ordinalPosition": 10,
      "name": "RTLS_OFF_YN",
      "type": "VARCHAR",
      "discontinued": false,
      "description": "If set to Yes, Real Time Location System (RTLS) tracking has manually been turned off for this provider on this case log.",
      "entries": [
        "No",
        "Yes"
      ]
    },
    {
      "ordinalPosition": 11,
      "name": "TIME_SOURCE_STATUS_C_NAME",
      "type": "VARCHAR",
      "discontinued": false,
      "description": "The source (Manual / RTLS) and status category of this row's start and end time.",
      "entries": [
        "Manual/Active",
        "RTLS/Active",
        "RTLS/Denied",
        "RTLS/Raw Event",
        "RTLS/Unresolved",
        "Manual/PageRespond"
      ]
    },
    {
      "ordinalPosition": 12,
      "name": "START_TIME_CMT",
      "type": "VARCHAR",
      "discontinued": false,
      "description": "The start time comment for the surgeon in the surgical log."
    },
    {
      "ordinalPosition": 13,
      "name": "END_TIME_CMT",
      "type": "VARCHAR",
      "discontinued": false,
      "description": "The end time comment for the surgeon in the surgical log."
    },
    {
      "ordinalPosition": 14,
      "name": "START_TIME_DOCU_ID",
      "type": "VARCHAR",
      "discontinued": false,
      "description": "The unique ID of the EMP user who documented the start time for each surgeon associated with any panel of the surgical log."
    },
    {
      "ordinalPosition": 15,
      "name": "START_TIME_DOCU_ID_NAME",
      "type": "VARCHAR",
      "discontinued": false,
      "description": "The name of the user record. This name may be hidden."
    },
    {
      "ordinalPosition": 16,
      "name": "END_TIME_DOCU_ID",
      "type": "VARCHAR",
      "discontinued": false,
      "description": "The unique ID of the EMP user who documented the end time for each surgeon associated with any panel of the surgical log."
    },
    {
      "ordinalPosition": 17,
      "name": "END_TIME_DOCU_ID_NAME",
      "type": "VARCHAR",
      "discontinued": false,
      "description": "The name of the user record. This name may be hidden."
    }
  ]
}
