{
  "name": "RSH_RESEARCH_INFO",
  "description": "This table contains information about research study administrative records.",
  "primaryKey": [
    {
      "columnName": "RESEARCH_ID",
      "ordinalPosition": 1
    }
  ],
  "columns": [
    {
      "ordinalPosition": 1,
      "name": "RESEARCH_ID",
      "type": "VARCHAR",
      "discontinued": false,
      "description": "The unique ID number of research study record."
    },
    {
      "ordinalPosition": 2,
      "name": "RESEARCH_STUDY_NAME",
      "type": "VARCHAR",
      "discontinued": false,
      "description": "The name of the research study record."
    }
  ]
}
